ikigai/__about__.py
ikigai/__init__.py
ikigai/ikigai.py
ikigai/client/__init__.py
ikigai/client/api.py
ikigai/client/client.py
ikigai/client/session.py
ikigai/components/__init__.py
ikigai/components/app.py
ikigai/components/dataset.py
ikigai/components/flow.py
ikigai/components/flow_definition.py
ikigai/components/model.py
ikigai/components/specs.py
ikigai/typing/__init__.py
ikigai/typing/api.py
ikigai/typing/protocol/__init__.py
ikigai/typing/protocol/app.py
ikigai/typing/protocol/dataset.py
ikigai/typing/protocol/directory.py
ikigai/typing/protocol/flow.py
ikigai/typing/protocol/generic.py
ikigai/typing/protocol/model.py
ikigai/utils/__init__.py
ikigai/utils/compatibility.py
ikigai/utils/component_browser.py
ikigai/utils/config.py
ikigai/utils/custom_serializers.py
ikigai/utils/custom_validators.py
ikigai/utils/data_structures.py
ikigai/utils/enums.py
ikigai/utils/helpful.py
ikigai/utils/missing.py
ikigai/utils/named_mapping.py
ikigai/utils/shim.py
ikigai-0.3.0.dist-info/METADATA
ikigai-0.3.0.dist-info/WHEEL
ikigai-0.3.0.dist-info/licenses/LICENSE.txt
ikigai-0.3.0.dist-info/RECORD
