Metadata-Version: 2.4
Name: ikigai
Version: 0.3.0
Summary: Python client for ikigailabs
Project-URL: Documentation, https://github.com/ikigailabs-io/ikigai#readme
Project-URL: Issues, https://github.com/ikigailabs-io/ikigai/issues
Project-URL: Source, https://github.com/ikigailabs-io/ikigai
Author-email: Harsh Parekh <harsh@ikigailabs.io>
License-Expression: MIT
License-File: LICENSE.txt
Classifier: Development Status :: 4 - Beta
Classifier: Programming Language :: Python
Classifier: Programming Language :: Python :: 3.10
Classifier: Programming Language :: Python :: 3.11
Classifier: Programming Language :: Python :: 3.12
Classifier: Programming Language :: Python :: 3.13
Classifier: Programming Language :: Python :: Implementation :: CPython
Classifier: Programming Language :: Python :: Implementation :: PyPy
Requires-Python: >=3.10
Requires-Dist: backports-strenum<2.0,>=1.3.1; python_version < '3.11'
Requires-Dist: deprecated; python_version < '3.13'
Requires-Dist: email-validator
Requires-Dist: eval-type-backport; python_version < '3.11'
Requires-Dist: pandas>=1.5
Requires-Dist: pydantic>=2.0
Requires-Dist: requests>=2.32
Requires-Dist: tomli; python_version < '3.11'
Requires-Dist: tqdm
